rt1_model/__init__.py
rt1_model/_calc.py
rt1_model/_numpydoc_docscrape.py
rt1_model/_scatter.py
rt1_model/helpers.py
rt1_model/plot.py
rt1_model/surface.py
rt1_model/volume.py
rt1_model-0.5.dist-info/LICENSE
rt1_model-0.5.dist-info/METADATA
rt1_model-0.5.dist-info/WHEEL
rt1_model-0.5.dist-info/top_level.txt
rt1_model-0.5.dist-info/RECORD
